seriesbr/.coverage
seriesbr/__init__.py
seriesbr/bcb/__init__.py
seriesbr/bcb/metadata.py
seriesbr/bcb/series.py
seriesbr/ibge/__init__.py
seriesbr/ibge/metadata.py
seriesbr/ibge/series.py
seriesbr/ipea/__init__.py
seriesbr/ipea/metadata.py
seriesbr/ipea/series.py
seriesbr/utils/__init__.py
seriesbr/utils/dates.py
seriesbr/utils/session.py
seriesbr-1.0.0.dist-info/LICENSE
seriesbr-1.0.0.dist-info/WHEEL
seriesbr-1.0.0.dist-info/METADATA
seriesbr-1.0.0.dist-info/RECORD
