Metadata-Version: 2.1
Name: seriesbr
Version: 1.0.0
Summary: A Python library to interact with brazilian time series databases
Home-page: https://github.com/phelipetls/seriesbr
License: MIT
Author: Phelipe Teles
Author-email: phelipe_teles@hotmail.com
Requires-Python: >=3.8,<4.0
Classifier: License :: OSI Approved :: MIT License
Classifier: Programming Language :: Python :: 3
Classifier: Programming Language :: Python :: 3.10
Classifier: Programming Language :: Python :: 3.8
Classifier: Programming Language :: Python :: 3.9
Requires-Dist: pandas (>=1.3.5,<2.0.0)
Requires-Dist: python-dateutil (>=2.8.2,<3.0.0)
Requires-Dist: requests (>=2.27.1,<3.0.0)
Requires-Dist: rope (>=0.22.0,<0.23.0)
Project-URL: Documentation, https://seriesbr.readthedocs.io/
Project-URL: Repository, https://github.com/phelipetls/seriesbr
